fastapi_sqlalchemy_filter/__init__.py
fastapi_sqlalchemy_filter/base_filter.py
fastapi_sqlalchemy_filter/filter.py
fastapi_sqlalchemy_filter/py.typed
fastapi_sqlalchemy_filter-0.2.5.dist-info/LICENSE.txt
fastapi_sqlalchemy_filter-0.2.5.dist-info/METADATA
fastapi_sqlalchemy_filter-0.2.5.dist-info/WHEEL
fastapi_sqlalchemy_filter-0.2.5.dist-info/top_level.txt
fastapi_sqlalchemy_filter-0.2.5.dist-info/RECORD
