Metadata-Version: 2.1
Name: fastapi-sqlalchemy-filter
Version: 0.2.5
Summary: A lite version of fastapi-filter for SQLAlchemy only
Home-page: https://github.com/waruingugi/fastapi-filter-sqlalchemy-lite/tree/sqlalchemy-filter-lite
Download-URL: https://github.com/waruingugi/fastapi-filter-sqlalchemy-lite/archive/refs/tags/v0.2.6.tar.gz
Author: Warui
Author-email: waruingugientp@gmail.com
Project-URL: Bug Tracker, https://github.com/waruingugi/fastapi-filter-sqlalchemy-lite/issues
Keywords: FastAPI,SQLAlchemy,Filter
Classifier: Natural Language :: English
Classifier: Framework :: FastAPI
Classifier: Operating System :: OS Independent
Classifier: Programming Language :: Python
Classifier: Programming Language :: Python :: 3
Classifier: Programming Language :: Python :: 3.8
Classifier: Programming Language :: Python :: 3.9
Classifier: Programming Language :: Python :: 3.10
Classifier: Programming Language :: Python :: 3.11
Classifier: Programming Language :: Python :: 3 :: Only
License-File: LICENSE.txt
Requires-Dist: pydantic
Requires-Dist: fastapi
Requires-Dist: sqlalchemy
